{
  "version": "5",
  "dialect": "mysql",
  "id": "cb9c3674-c2a0-4492-a8fe-e4c1ed1aae18",
  "prevId": "08b6b6ea-3c95-4536-8977-0502ecfaef59",
  "tables": {
    "application_polls": {
      "name": "application_polls",
      "columns": {
        "ref": {
          "name": "ref",
          "type": "int",
          "primaryKey": false,
          "notNull": true,
          "autoincrement": false
        },
        "thread": {
          "name": "thread",
          "type": "varchar(20)",
          "primaryKey": false,
          "notNull": true,
          "autoincrement": false
        }
      },
      "indexes": {},
      "foreignKeys": {
        "application_polls_ref_polls_id_fk": {
          "name": "application_polls_ref_polls_id_fk",
          "tableFrom": "application_polls",
          "tableTo": "polls",
          "columnsFrom": [
            "ref"
          ],
          "columnsTo": [
            "id"
          ],
          "onDelete": "cascade",
          "onUpdate": "cascade"
        },
        "application_polls_thread_applications_thread_fk": {
          "name": "application_polls_thread_applications_thread_fk",
          "tableFrom": "application_polls",
          "tableTo": "applications",
          "columnsFrom": [
            "thread"
          ],
          "columnsTo": [
            "thread"
          ],
          "onDelete": "cascade",
          "onUpdate": "cascade"
        }
      },
      "compositePrimaryKeys": {
        "application_polls_ref": {
          "name": "application_polls_ref",
          "columns": [
            "ref"
          ]
        }
      },
      "uniqueConstraints": {}
    },
    "applications": {
      "name": "applications",
      "columns": {
        "thread": {
          "name": "thread",
          "type": "varchar(20)",
          "primaryKey": false,
          "notNull": true,
          "autoincrement": false
        },
        "guild": {
          "name": "guild",
          "type": "varchar(20)",
          "primaryKey": false,
          "notNull": true,
          "autoincrement": false
        },
        "invite": {
          "name": "invite",
          "type": "text",
          "primaryKey": false,
          "notNull": true,
          "autoincrement": false
        },
        "url": {
          "name": "url",
          "type": "varchar(128)",
          "primaryKey": false,
          "notNull": true,
          "autoincrement": false
        },
        "user": {
          "name": "user",
          "type": "varchar(20)",
          "primaryKey": false,
          "notNull": true,
          "autoincrement": false
        },
        "name": {
          "name": "name",
          "type": "text",
          "primaryKey": false,
          "notNull": true,
          "autoincrement": false
        },
        "experience": {
          "name": "experience",
          "type": "varchar(1024)",
          "primaryKey": false,
          "notNull": true,
          "autoincrement": false
        },
        "goals": {
          "name": "goals",
          "type": "varchar(1024)",
          "primaryKey": false,
          "notNull": true,
          "autoincrement": false
        },
        "history": {
          "name": "history",
          "type": "varchar(1024)",
          "primaryKey": false,
          "notNull": true,
          "autoincrement": false
        },
        "additional": {
          "name": "additional",
          "type": "varchar(1024)",
          "primaryKey": false,
          "notNull": true,
          "autoincrement": false
        }
      },
      "indexes": {},
      "foreignKeys": {},
      "compositePrimaryKeys": {
        "applications_thread": {
          "name": "applications_thread",
          "columns": [
            "thread"
          ]
        }
      },
      "uniqueConstraints": {}
    },
    "audit_entry_targets": {
      "name": "audit_entry_targets",
      "columns": {
        "target": {
          "name": "target",
          "type": "varchar(20)",
          "primaryKey": false,
          "notNull": true,
          "autoincrement": false
        },
        "ref": {
          "name": "ref",
          "type": "int",
          "primaryKey": false,
          "notNull": true,
          "autoincrement": false
        }
      },
      "indexes": {
        "idx_target": {
          "name": "idx_target",
          "columns": [
            "target"
          ],
          "isUnique": false
        }
      },
      "foreignKeys": {
        "audit_entry_targets_ref_audit_logs_id_fk": {
          "name": "audit_entry_targets_ref_audit_logs_id_fk",
          "tableFrom": "audit_entry_targets",
          "tableTo": "audit_logs",
          "columnsFrom": [
            "ref"
          ],
          "columnsTo": [
            "id"
          ],
          "onDelete": "cascade",
          "onUpdate": "cascade"
        }
      },
      "compositePrimaryKeys": {},
      "uniqueConstraints": {}
    },
    "audit_logs": {
      "name": "audit_logs",
      "columns": {
        "id": {
          "name": "id",
          "type": "int",
          "primaryKey": false,
          "notNull": true,
          "autoincrement": true
        },
        "time": {
          "name": "time",
          "type": "bigint",
          "primaryKey": false,
          "notNull": true,
          "autoincrement": false
        },
        "actor": {
          "name": "actor",
          "type": "varchar(20)",
          "primaryKey": false,
          "notNull": true,
          "autoincrement": false
        },
        "type": {
          "name": "type",
          "type": "varchar(64)",
          "primaryKey": false,
          "notNull": true,
          "autoincrement": false
        },
        "guild": {
          "name": "guild",
          "type": "varchar(20)",
          "primaryKey": false,
          "notNull": false,
          "autoincrement": false
        },
        "data": {
          "name": "data",
          "type": "json",
          "primaryKey": false,
          "notNull": false,
          "autoincrement": false
        }
      },
      "indexes": {
        "idx_actor_guild_type": {
          "name": "idx_actor_guild_type",
          "columns": [
            "actor",
            "guild",
            "type"
          ],
          "isUnique": false
        },
        "idx_guild_type": {
          "name": "idx_guild_type",
          "columns": [
            "guild",
            "type"
          ],
          "isUnique": false
        },
        "idx_type": {
          "name": "idx_type",
          "columns": [
            "type"
          ],
          "isUnique": false
        }
      },
      "foreignKeys": {},
      "compositePrimaryKeys": {
        "audit_logs_id": {
          "name": "audit_logs_id",
          "columns": [
            "id"
          ]
        }
      },
      "uniqueConstraints": {}
    },
    "auto_staff_roles": {
      "name": "auto_staff_roles",
      "columns": {
        "guild": {
          "name": "guild",
          "type": "varchar(20)",
          "primaryKey": false,
          "notNull": true,
          "autoincrement": false
        },
        "role": {
          "name": "role",
          "type": "varchar(20)",
          "primaryKey": false,
          "notNull": true,
          "autoincrement": false
        }
      },
      "indexes": {},
      "foreignKeys": {
        "auto_staff_roles_guild_guilds_id_fk": {
          "name": "auto_staff_roles_guild_guilds_id_fk",
          "tableFrom": "auto_staff_roles",
          "tableTo": "guilds",
          "columnsFrom": [
            "guild"
          ],
          "columnsTo": [
            "id"
          ],
          "onDelete": "cascade",
          "onUpdate": "cascade"
        }
      },
      "compositePrimaryKeys": {
        "auto_staff_roles_guild_role_pk": {
          "name": "auto_staff_roles_guild_role_pk",
          "columns": [
            "guild",
            "role"
          ]
        }
      },
      "uniqueConstraints": {}
    },
    "autosync_settings": {
      "name": "autosync_settings",
      "columns": {
        "guild": {
          "name": "guild",
          "type": "varchar(20)",
          "primaryKey": false,
          "notNull": true,
          "autoincrement": false
        },
        "location": {
          "name": "location",
          "type": "enum('disabled','channel','webhook')",
          "primaryKey": false,
          "notNull": true,
          "autoincrement": false
        },
        "channel": {
          "name": "channel",
          "type": "varchar(20)",
          "primaryKey": false,
          "notNull": false,
          "autoincrement": false
        },
        "webhook": {
          "name": "webhook",
          "type": "text",
          "primaryKey": false,
          "notNull": false,
          "autoincrement": false
        },
        "message": {
          "name": "message",
          "type": "varchar(20)",
          "primaryKey": false,
          "notNull": false,
          "autoincrement": false
        },
        "repost": {
          "name": "repost",
          "type": "boolean",
          "primaryKey": false,
          "notNull": true,
          "autoincrement": false,
          "default": false
        }
      },
      "indexes": {},
      "foreignKeys": {
        "autosync_settings_guild_guilds_id_fk": {
          "name": "autosync_settings_guild_guilds_id_fk",
          "tableFrom": "autosync_settings",
          "tableTo": "guilds",
          "columnsFrom": [
            "guild"
          ],
          "columnsTo": [
            "id"
          ],
          "onDelete": "cascade",
          "onUpdate": "cascade"
        }
      },
      "compositePrimaryKeys": {
        "autosync_settings_guild": {
          "name": "autosync_settings_guild",
          "columns": [
            "guild"
          ]
        }
      },
      "uniqueConstraints": {}
    },
    "aux_global_authors": {
      "name": "aux_global_authors",
      "columns": {
        "message": {
          "name": "message",
          "type": "varchar(20)",
          "primaryKey": false,
          "notNull": true,
          "autoincrement": false
        },
        "user": {
          "name": "user",
          "type": "varchar(20)",
          "primaryKey": false,
          "notNull": true,
          "autoincrement": false
        }
      },
      "indexes": {},
      "foreignKeys": {},
      "compositePrimaryKeys": {
        "aux_global_authors_message": {
          "name": "aux_global_authors_message",
          "columns": [
            "message"
          ]
        }
      },
      "uniqueConstraints": {}
    },
    "ban_tasks": {
      "name": "ban_tasks",
      "columns": {
        "id": {
          "name": "id",
          "type": "int",
          "primaryKey": false,
          "notNull": true,
          "autoincrement": true
        },
        "ref": {
          "name": "ref",
          "type": "int",
          "primaryKey": false,
          "notNull": true,
          "autoincrement": false
        },
        "guild": {
          "name": "guild",
          "type": "varchar(20)",
          "primaryKey": false,
          "notNull": true,
          "autoincrement": false
        },
        "user": {
          "name": "user",
          "type": "varchar(20)",
          "primaryKey": false,
          "notNull": true,
          "autoincrement": false
        },
        "status": {
          "name": "status",
          "type": "enum('pending','skipped','banned','failed','hold')",
          "primaryKey": false,
          "notNull": true,
          "autoincrement": false
        },
        "member": {
          "name": "member",
          "type": "boolean",
          "primaryKey": false,
          "notNull": false,
          "autoincrement": false
        },
        "autoban": {
          "name": "autoban",
          "type": "boolean",
          "primaryKey": false,
          "notNull": true,
          "autoincrement": false
        }
      },
      "indexes": {},
      "foreignKeys": {
        "ban_tasks_ref_banshares_id_fk": {
          "name": "ban_tasks_ref_banshares_id_fk",
          "tableFrom": "ban_tasks",
          "tableTo": "banshares",
          "columnsFrom": [
            "ref"
          ],
          "columnsTo": [
            "id"
          ],
          "onDelete": "cascade",
          "onUpdate": "cascade"
        },
        "ban_tasks_guild_guilds_id_fk": {
          "name": "ban_tasks_guild_guilds_id_fk",
          "tableFrom": "ban_tasks",
          "tableTo": "guilds",
          "columnsFrom": [
            "guild"
          ],
          "columnsTo": [
            "id"
          ],
          "onDelete": "cascade",
          "onUpdate": "cascade"
        }
      },
      "compositePrimaryKeys": {
        "ban_tasks_id": {
          "name": "ban_tasks_id",
          "columns": [
            "id"
          ]
        }
      },
      "uniqueConstraints": {
        "idx_ref_guild_user": {
          "name": "idx_ref_guild_user",
          "columns": [
            "ref",
            "guild",
            "user"
          ]
        }
      }
    },
    "banlists": {
      "name": "banlists",
      "columns": {
        "uuid": {
          "name": "uuid",
          "type": "varchar(36)",
          "primaryKey": false,
          "notNull": true,
          "autoincrement": false
        },
        "content": {
          "name": "content",
          "type": "text",
          "primaryKey": false,
          "notNull": true,
          "autoincrement": false
        }
      },
      "indexes": {},
      "foreignKeys": {},
      "compositePrimaryKeys": {
        "banlists_uuid": {
          "name": "banlists_uuid",
          "columns": [
            "uuid"
          ]
        }
      },
      "uniqueConstraints": {}
    },
    "banshare_action_settings": {
      "name": "banshare_action_settings",
      "columns": {
        "guild": {
          "name": "guild",
          "type": "varchar(20)",
          "primaryKey": false,
          "notNull": true,
          "autoincrement": false
        },
        "severity": {
          "name": "severity",
          "type": "varchar(8)",
          "primaryKey": false,
          "notNull": true,
          "autoincrement": false
        },
        "member": {
          "name": "member",
          "type": "boolean",
          "primaryKey": false,
          "notNull": true,
          "autoincrement": false
        },
        "ban": {
          "name": "ban",
          "type": "boolean",
          "primaryKey": false,
          "notNull": true,
          "autoincrement": false
        }
      },
      "indexes": {},
      "foreignKeys": {
        "banshare_action_settings_guild_guilds_id_fk": {
          "name": "banshare_action_settings_guild_guilds_id_fk",
          "tableFrom": "banshare_action_settings",
          "tableTo": "guilds",
          "columnsFrom": [
            "guild"
          ],
          "columnsTo": [
            "id"
          ],
          "onDelete": "cascade",
          "onUpdate": "cascade"
        }
      },
      "compositePrimaryKeys": {
        "banshare_action_settings_guild_severity_member_pk": {
          "name": "banshare_action_settings_guild_severity_member_pk",
          "columns": [
            "guild",
            "severity",
            "member"
          ]
        }
      },
      "uniqueConstraints": {}
    },
    "banshare_crossposts": {
      "name": "banshare_crossposts",
      "columns": {
        "ref": {
          "name": "ref",
          "type": "int",
          "primaryKey": false,
          "notNull": true,
          "autoincrement": false
        },
        "guild": {
          "name": "guild",
          "type": "varchar(20)",
          "primaryKey": false,
          "notNull": true,
          "autoincrement": false
        },
        "channel": {
          "name": "channel",
          "type": "varchar(20)",
          "primaryKey": false,
          "notNull": true,
          "autoincrement": false
        },
        "message": {
          "name": "message",
          "type": "varchar(20)",
          "primaryKey": false,
          "notNull": true,
          "autoincrement": false
        },
        "executor": {
          "name": "executor",
          "type": "varchar(20)",
          "primaryKey": false,
          "notNull": false,
          "autoincrement": false
        }
      },
      "indexes": {},
      "foreignKeys": {
        "banshare_crossposts_ref_banshares_id_fk": {
          "name": "banshare_crossposts_ref_banshares_id_fk",
          "tableFrom": "banshare_crossposts",
          "tableTo": "banshares",
          "columnsFrom": [
            "ref"
          ],
          "columnsTo": [
            "id"
          ],
          "onDelete": "cascade",
          "onUpdate": "cascade"
        },
        "banshare_crossposts_guild_guilds_id_fk": {
          "name": "banshare_crossposts_guild_guilds_id_fk",
          "tableFrom": "banshare_crossposts",
          "tableTo": "guilds",
          "columnsFrom": [
            "guild"
          ],
          "columnsTo": [
            "id"
          ],
          "onDelete": "cascade",
          "onUpdate": "cascade"
        }
      },
      "compositePrimaryKeys": {
        "banshare_crossposts_ref_guild_pk": {
          "name": "banshare_crossposts_ref_guild_pk",
          "columns": [
            "ref",
            "guild"
          ]
        }
      },
      "uniqueConstraints": {}
    },
    "banshare_hub_posts": {
      "name": "banshare_hub_posts",
      "columns": {
        "ref": {
          "name": "ref",
          "type": "int",
          "primaryKey": false,
          "notNull": true,
          "autoincrement": false
        },
        "channel": {
          "name": "channel",
          "type": "varchar(20)",
          "primaryKey": false,
          "notNull": true,
          "autoincrement": false
        },
        "message": {
          "name": "message",
          "type": "varchar(20)",
          "primaryKey": false,
          "notNull": true,
          "autoincrement": false
        }
      },
      "indexes": {},
      "foreignKeys": {
        "banshare_hub_posts_ref_banshares_id_fk": {
          "name": "banshare_hub_posts_ref_banshares_id_fk",
          "tableFrom": "banshare_hub_posts",
          "tableTo": "banshares",
          "columnsFrom": [
            "ref"
          ],
          "columnsTo": [
            "id"
          ],
          "onDelete": "cascade",
          "onUpdate": "cascade"
        }
      },
      "compositePrimaryKeys": {
        "banshare_hub_posts_ref": {
          "name": "banshare_hub_posts_ref",
          "columns": [
            "ref"
          ]
        }
      },
      "uniqueConstraints": {}
    },
    "banshare_ids": {
      "name": "banshare_ids",
      "columns": {
        "ref": {
          "name": "ref",
          "type": "int",
          "primaryKey": false,
          "notNull": true,
          "autoincrement": false
        },
        "user": {
          "name": "user",
          "type": "varchar(20)",
          "primaryKey": false,
          "notNull": true,
          "autoincrement": false
        }
      },
      "indexes": {},
      "foreignKeys": {
        "banshare_ids_ref_banshares_id_fk": {
          "name": "banshare_ids_ref_banshares_id_fk",
          "tableFrom": "banshare_ids",
          "tableTo": "banshares",
          "columnsFrom": [
            "ref"
          ],
          "columnsTo": [
            "id"
          ],
          "onDelete": "cascade",
          "onUpdate": "cascade"
        }
      },
      "compositePrimaryKeys": {
        "banshare_ids_ref_user_pk": {
          "name": "banshare_ids_ref_user_pk",
          "columns": [
            "ref",
            "user"
          ]
        }
      },
      "uniqueConstraints": {}
    },
    "banshare_settings": {
      "name": "banshare_settings",
      "columns": {
        "guild": {
          "name": "guild",
          "type": "varchar(20)",
          "primaryKey": false,
          "notNull": true,
          "autoincrement": false
        },
        "channel": {
          "name": "channel",
          "type": "varchar(20)",
          "primaryKey": false,
          "notNull": false,
          "autoincrement": false
        },
        "logs": {
          "name": "logs",
          "type": "varchar(20)",
          "primaryKey": false,
          "notNull": false,
          "autoincrement": false
        }
      },
      "indexes": {},
      "foreignKeys": {
        "banshare_settings_guild_guilds_id_fk": {
          "name": "banshare_settings_guild_guilds_id_fk",
          "tableFrom": "banshare_settings",
          "tableTo": "guilds",
          "columnsFrom": [
            "guild"
          ],
          "columnsTo": [
            "id"
          ],
          "onDelete": "cascade",
          "onUpdate": "cascade"
        }
      },
      "compositePrimaryKeys": {
        "banshare_settings_guild": {
          "name": "banshare_settings_guild",
          "columns": [
            "guild"
          ]
        }
      },
      "uniqueConstraints": {}
    },
    "banshares": {
      "name": "banshares",
      "columns": {
        "id": {
          "name": "id",
          "type": "int",
          "primaryKey": false,
          "notNull": true,
          "autoincrement": true
        },
        "message": {
          "name": "message",
          "type": "varchar(20)",
          "primaryKey": false,
          "notNull": true,
          "autoincrement": false
        },
        "author": {
          "name": "author",
          "type": "varchar(20)",
          "primaryKey": false,
          "notNull": true,
          "autoincrement": false
        },
        "display": {
          "name": "display",
          "type": "varchar(1024)",
          "primaryKey": false,
          "notNull": true,
          "autoincrement": false
        },
        "usernames": {
          "name": "usernames",
          "type": "varchar(1024)",
          "primaryKey": false,
          "notNull": true,
          "autoincrement": false
        },
        "reason": {
          "name": "reason",
          "type": "varchar(498)",
          "primaryKey": false,
          "notNull": true,
          "autoincrement": false
        },
        "evidence": {
          "name": "evidence",
          "type": "varchar(1000)",
          "primaryKey": false,
          "notNull": true,
          "autoincrement": false
        },
        "server": {
          "name": "server",
          "type": "varchar(20)",
          "primaryKey": false,
          "notNull": true,
          "autoincrement": false
        },
        "severity": {
          "name": "severity",
          "type": "varchar(8)",
          "primaryKey": false,
          "notNull": true,
          "autoincrement": false
        },
        "urgent": {
          "name": "urgent",
          "type": "boolean",
          "primaryKey": false,
          "notNull": true,
          "autoincrement": false
        },
        "reminded": {
          "name": "reminded",
          "type": "bigint",
          "primaryKey": false,
          "notNull": true,
          "autoincrement": false
        },
        "status": {
          "name": "status",
          "type": "enum('pending','locked','rejected','published','rescinded')",
          "primaryKey": false,
          "notNull": true,
          "autoincrement": false
        }
      },
      "indexes": {
        "idx_message": {
          "name": "idx_message",
          "columns": [
            "message"
          ],
          "isUnique": false
        }
      },
      "foreignKeys": {},
      "compositePrimaryKeys": {
        "banshares_id": {
          "name": "banshares_id",
          "columns": [
            "id"
          ]
        }
      },
      "uniqueConstraints": {}
    },
    "cancel_observation_votes": {
      "name": "cancel_observation_votes",
      "columns": {
        "ref": {
          "name": "ref",
          "type": "int",
          "primaryKey": false,
          "notNull": true,
          "autoincrement": false
        },
        "user": {
          "name": "user",
          "type": "varchar(20)",
          "primaryKey": false,
          "notNull": true,
          "autoincrement": false
        },
        "vote": {
          "name": "vote",
          "type": "enum('cancel','continue','abstain')",
          "primaryKey": false,
          "notNull": true,
          "autoincrement": false
        }
      },
      "indexes": {},
      "foreignKeys": {
        "cancel_observation_votes_ref_polls_id_fk": {
          "name": "cancel_observation_votes_ref_polls_id_fk",
          "tableFrom": "cancel_observation_votes",
          "tableTo": "polls",
          "columnsFrom": [
            "ref"
          ],
          "columnsTo": [
            "id"
          ],
          "onDelete": "cascade",
          "onUpdate": "cascade"
        }
      },
      "compositePrimaryKeys": {
        "cancel_observation_votes_ref_user_pk": {
          "name": "cancel_observation_votes_ref_user_pk",
          "columns": [
            "ref",
            "user"
          ]
        }
      },
      "uniqueConstraints": {}
    },
    "characters": {
      "name": "characters",
      "columns": {
        "id": {
          "name": "id",
          "type": "varchar(32)",
          "primaryKey": false,
          "notNull": true,
          "autoincrement": false
        },
        "short": {
          "name": "short",
          "type": "varchar(32)",
          "primaryKey": false,
          "notNull": false,
          "autoincrement": false
        },
        "name": {
          "name": "name",
          "type": "varchar(64)",
          "primaryKey": false,
          "notNull": true,
          "autoincrement": false
        },
        "element": {
          "name": "element",
          "type": "varchar(32)",
          "primaryKey": false,
          "notNull": true,
          "autoincrement": false
        }
      },
      "indexes": {},
      "foreignKeys": {},
      "compositePrimaryKeys": {
        "characters_id": {
          "name": "characters_id",
          "columns": [
            "id"
          ]
        }
      },
      "uniqueConstraints": {}
    },
    "decline_observation_votes": {
      "name": "decline_observation_votes",
      "columns": {
        "ref": {
          "name": "ref",
          "type": "int",
          "primaryKey": false,
          "notNull": true,
          "autoincrement": false
        },
        "user": {
          "name": "user",
          "type": "varchar(20)",
          "primaryKey": false,
          "notNull": true,
          "autoincrement": false
        },
        "vote": {
          "name": "vote",
          "type": "enum('decline','proceed','abstain')",
          "primaryKey": false,
          "notNull": true,
          "autoincrement": false
        }
      },
      "indexes": {},
      "foreignKeys": {
        "decline_observation_votes_ref_polls_id_fk": {
          "name": "decline_observation_votes_ref_polls_id_fk",
          "tableFrom": "decline_observation_votes",
          "tableTo": "polls",
          "columnsFrom": [
            "ref"
          ],
          "columnsTo": [
            "id"
          ],
          "onDelete": "cascade",
          "onUpdate": "cascade"
        }
      },
      "compositePrimaryKeys": {
        "decline_observation_votes_ref_user_pk": {
          "name": "decline_observation_votes_ref_user_pk",
          "columns": [
            "ref",
            "user"
          ]
        }
      },
      "uniqueConstraints": {}
    },
    "election_history": {
      "name": "election_history",
      "columns": {
        "wave": {
          "name": "wave",
          "type": "int",
          "primaryKey": false,
          "notNull": true,
          "autoincrement": false
        },
        "user": {
          "name": "user",
          "type": "varchar(20)",
          "primaryKey": false,
          "notNull": true,
          "autoincrement": false
        },
        "status": {
          "name": "status",
          "type": "enum('nominated','accepted','declined','elected','tied','runner-up')",
          "primaryKey": false,
          "notNull": true,
          "autoincrement": false
        },
        "rerunning": {
          "name": "rerunning",
          "type": "boolean",
          "primaryKey": false,
          "notNull": true,
          "autoincrement": false
        }
      },
      "indexes": {},
      "foreignKeys": {
        "election_history_wave_elections_wave_fk": {
          "name": "election_history_wave_elections_wave_fk",
          "tableFrom": "election_history",
          "tableTo": "elections",
          "columnsFrom": [
            "wave"
          ],
          "columnsTo": [
            "wave"
          ],
          "onDelete": "cascade",
          "onUpdate": "cascade"
        }
      },
      "compositePrimaryKeys": {
        "election_history_wave_user_pk": {
          "name": "election_history_wave_user_pk",
          "columns": [
            "wave",
            "user"
          ]
        }
      },
      "uniqueConstraints": {}
    },
    "election_polls": {
      "name": "election_polls",
      "columns": {
        "ref": {
          "name": "ref",
          "type": "int",
          "primaryKey": false,
          "notNull": true,
          "autoincrement": false
        },
        "thread": {
          "name": "thread",
          "type": "varchar(20)",
          "primaryKey": false,
          "notNull": true,
          "autoincrement": false
        },
        "candidates": {
          "name": "candidates",
          "type": "json",
          "primaryKey": false,
          "notNull": true,
          "autoincrement": false
        },
        "autopromoted": {
          "name": "autopromoted",
          "type": "boolean",
          "primaryKey": false,
          "notNull": true,
          "autoincrement": false,
          "default": false
        }
      },
      "indexes": {
        "idx_thread": {
          "name": "idx_thread",
          "columns": [
            "thread"
          ],
          "isUnique": false
        }
      },
      "foreignKeys": {
        "election_polls_ref_polls_id_fk": {
          "name": "election_polls_ref_polls_id_fk",
          "tableFrom": "election_polls",
          "tableTo": "polls",
          "columnsFrom": [
            "ref"
          ],
          "columnsTo": [
            "id"
          ],
          "onDelete": "cascade",
          "onUpdate": "cascade"
        },
        "election_polls_thread_elections_channel_fk": {
          "name": "election_polls_thread_elections_channel_fk",
          "tableFrom": "election_polls",
          "tableTo": "elections",
          "columnsFrom": [
            "thread"
          ],
          "columnsTo": [
            "channel"
          ],
          "onDelete": "cascade",
          "onUpdate": "cascade"
        }
      },
      "compositePrimaryKeys": {
        "election_polls_ref": {
          "name": "election_polls_ref",
          "columns": [
            "ref"
          ]
        }
      },
      "uniqueConstraints": {}
    },
    "election_statements": {
      "name": "election_statements",
      "columns": {
        "wave": {
          "name": "wave",
          "type": "int",
          "primaryKey": false,
          "notNull": true,
          "autoincrement": false
        },
        "user": {
          "name": "user",
          "type": "varchar(20)",
          "primaryKey": false,
          "notNull": true,
          "autoincrement": false
        },
        "message": {
          "name": "message",
          "type": "varchar(20)",
          "primaryKey": false,
          "notNull": true,
          "autoincrement": false
        }
      },
      "indexes": {},
      "foreignKeys": {
        "election_statements_wave_elections_wave_fk": {
          "name": "election_statements_wave_elections_wave_fk",
          "tableFrom": "election_statements",
          "tableTo": "elections",
          "columnsFrom": [
            "wave"
          ],
          "columnsTo": [
            "wave"
          ],
          "onDelete": "cascade",
          "onUpdate": "cascade"
        }
      },
      "compositePrimaryKeys": {
        "election_statements_wave_user_pk": {
          "name": "election_statements_wave_user_pk",
          "columns": [
            "wave",
            "user"
          ]
        }
      },
      "uniqueConstraints": {}
    },
    "election_votes": {
      "name": "election_votes",
      "columns": {
        "ref": {
          "name": "ref",
          "type": "int",
          "primaryKey": false,
          "notNull": true,
          "autoincrement": false
        },
        "user": {
          "name": "user",
          "type": "varchar(20)",
          "primaryKey": false,
          "notNull": true,
          "autoincrement": false
        },
        "vote": {
          "name": "vote",
          "type": "json",
          "primaryKey": false,
          "notNull": true,
          "autoincrement": false
        }
      },
      "indexes": {},
      "foreignKeys": {
        "election_votes_ref_polls_id_fk": {
          "name": "election_votes_ref_polls_id_fk",
          "tableFrom": "election_votes",
          "tableTo": "polls",
          "columnsFrom": [
            "ref"
          ],
          "columnsTo": [
            "id"
          ],
          "onDelete": "cascade",
          "onUpdate": "cascade"
        }
      },
      "compositePrimaryKeys": {
        "election_votes_ref_user_pk": {
          "name": "election_votes_ref_user_pk",
          "columns": [
            "ref",
            "user"
          ]
        }
      },
      "uniqueConstraints": {}
    },
    "elections": {
      "name": "elections",
      "columns": {
        "wave": {
          "name": "wave",
          "type": "int",
          "primaryKey": false,
          "notNull": true,
          "autoincrement": false
        },
        "channel": {
          "name": "channel",
          "type": "varchar(20)",
          "primaryKey": false,
          "notNull": true,
          "autoincrement": false
        },
        "seats": {
          "name": "seats",
          "type": "int",
          "primaryKey": false,
          "notNull": true,
          "autoincrement": false
        }
      },
      "indexes": {
        "idx_channel": {
          "name": "idx_channel",
          "columns": [
            "channel"
          ],
          "isUnique": false
        }
      },
      "foreignKeys": {},
      "compositePrimaryKeys": {
        "elections_wave": {
          "name": "elections_wave",
          "columns": [
            "wave"
          ]
        }
      },
      "uniqueConstraints": {}
    },
    "expected_voters": {
      "name": "expected_voters",
      "columns": {
        "poll": {
          "name": "poll",
          "type": "int",
          "primaryKey": false,
          "notNull": true,
          "autoincrement": false
        },
        "user": {
          "name": "user",
          "type": "varchar(20)",
          "primaryKey": false,
          "notNull": true,
          "autoincrement": false
        }
      },
      "indexes": {},
      "foreignKeys": {
        "expected_voters_poll_polls_id_fk": {
          "name": "expected_voters_poll_polls_id_fk",
          "tableFrom": "expected_voters",
          "tableTo": "polls",
          "columnsFrom": [
            "poll"
          ],
          "columnsTo": [
            "id"
          ],
          "onDelete": "cascade",
          "onUpdate": "cascade"
        }
      },
      "compositePrimaryKeys": {
        "expected_voters_poll_user_pk": {
          "name": "expected_voters_poll_user_pk",
          "columns": [
            "poll",
            "user"
          ]
        }
      },
      "uniqueConstraints": {}
    },
    "files": {
      "name": "files",
      "columns": {
        "uuid": {
          "name": "uuid",
          "type": "varchar(36)",
          "primaryKey": false,
          "notNull": true,
          "autoincrement": false
        },
        "channel": {
          "name": "channel",
          "type": "varchar(20)",
          "primaryKey": false,
          "notNull": true,
          "autoincrement": false
        },
        "message": {
          "name": "message",
          "type": "varchar(20)",
          "primaryKey": false,
          "notNull": true,
          "autoincrement": false
        }
      },
      "indexes": {},
      "foreignKeys": {},
      "compositePrimaryKeys": {
        "files_uuid": {
          "name": "files_uuid",
          "columns": [
            "uuid"
          ]
        }
      },
      "uniqueConstraints": {}
    },
    "forced_staff": {
      "name": "forced_staff",
      "columns": {
        "guild": {
          "name": "guild",
          "type": "varchar(20)",
          "primaryKey": false,
          "notNull": true,
          "autoincrement": false
        },
        "user": {
          "name": "user",
          "type": "varchar(20)",
          "primaryKey": false,
          "notNull": true,
          "autoincrement": false
        },
        "staff": {
          "name": "staff",
          "type": "boolean",
          "primaryKey": false,
          "notNull": true,
          "autoincrement": false
        }
      },
      "indexes": {},
      "foreignKeys": {
        "forced_staff_guild_guilds_id_fk": {
          "name": "forced_staff_guild_guilds_id_fk",
          "tableFrom": "forced_staff",
          "tableTo": "guilds",
          "columnsFrom": [
            "guild"
          ],
          "columnsTo": [
            "id"
          ],
          "onDelete": "cascade",
          "onUpdate": "cascade"
        }
      },
      "compositePrimaryKeys": {
        "forced_staff_guild_user_pk": {
          "name": "forced_staff_guild_user_pk",
          "columns": [
            "guild",
            "user"
          ]
        }
      },
      "uniqueConstraints": {}
    },
    "global_applied_filters": {
      "name": "global_applied_filters",
      "columns": {
        "channel": {
          "name": "channel",
          "type": "int",
          "primaryKey": false,
          "notNull": true,
          "autoincrement": false
        },
        "filter": {
          "name": "filter",
          "type": "int",
          "primaryKey": false,
          "notNull": true,
          "autoincrement": false
        }
      },
      "indexes": {},
      "foreignKeys": {
        "global_applied_filters_channel_global_channels_id_fk": {
          "name": "global_applied_filters_channel_global_channels_id_fk",
          "tableFrom": "global_applied_filters",
          "tableTo": "global_channels",
          "columnsFrom": [
            "channel"
          ],
          "columnsTo": [
            "id"
          ],
          "onDelete": "cascade",
          "onUpdate": "cascade"
        },
        "global_applied_filters_filter_global_filters_id_fk": {
          "name": "global_applied_filters_filter_global_filters_id_fk",
          "tableFrom": "global_applied_filters",
          "tableTo": "global_filters",
          "columnsFrom": [
            "filter"
          ],
          "columnsTo": [
            "id"
          ],
          "onDelete": "cascade",
          "onUpdate": "cascade"
        }
      },
      "compositePrimaryKeys": {
        "global_applied_filters_channel_filter_pk": {
          "name": "global_applied_filters_channel_filter_pk",
          "columns": [
            "channel",
            "filter"
          ]
        }
      },
      "uniqueConstraints": {}
    },
    "global_bans": {
      "name": "global_bans",
      "columns": {
        "channel": {
          "name": "channel",
          "type": "int",
          "primaryKey": false,
          "notNull": true,
          "autoincrement": false
        },
        "user": {
          "name": "user",
          "type": "varchar(20)",
          "primaryKey": false,
          "notNull": true,
          "autoincrement": false
        }
      },
      "indexes": {},
      "foreignKeys": {
        "global_bans_channel_global_channels_id_fk": {
          "name": "global_bans_channel_global_channels_id_fk",
          "tableFrom": "global_bans",
          "tableTo": "global_channels",
          "columnsFrom": [
            "channel"
          ],
          "columnsTo": [
            "id"
          ],
          "onDelete": "cascade",
          "onUpdate": "cascade"
        }
      },
      "compositePrimaryKeys": {
        "global_bans_channel_user_pk": {
          "name": "global_bans_channel_user_pk",
          "columns": [
            "channel",
            "user"
          ]
        }
      },
      "uniqueConstraints": {}
    },
    "global_channels": {
      "name": "global_channels",
      "columns": {
        "id": {
          "name": "id",
          "type": "int",
          "primaryKey": false,
          "notNull": true,
          "autoincrement": true
        },
        "name": {
          "name": "name",
          "type": "varchar(80)",
          "primaryKey": false,
          "notNull": true,
          "autoincrement": false
        },
        "visible": {
          "name": "visible",
          "type": "boolean",
          "primaryKey": false,
          "notNull": true,
          "autoincrement": false
        },
        "password": {
          "name": "password",
          "type": "varchar(128)",
          "primaryKey": false,
          "notNull": false,
          "autoincrement": false
        },
        "panic": {
          "name": "panic",
          "type": "boolean",
          "primaryKey": false,
          "notNull": true,
          "autoincrement": false,
          "default": false
        },
        "protected": {
          "name": "protected",
          "type": "boolean",
          "primaryKey": false,
          "notNull": true,
          "autoincrement": false,
          "default": false
        },
        "important": {
          "name": "important",
          "type": "boolean",
          "primaryKey": false,
          "notNull": true,
          "autoincrement": false,
          "default": false
        },
        "info_on_user_plugin": {
          "name": "info_on_user_plugin",
          "type": "boolean",
          "primaryKey": false,
          "notNull": true,
          "autoincrement": false,
          "default": false
        },
        "logs": {
          "name": "logs",
          "type": "varchar(20)",
          "primaryKey": false,
          "notNull": false,
          "autoincrement": false
        }
      },
      "indexes": {},
      "foreignKeys": {},
      "compositePrimaryKeys": {
        "global_channels_id": {
          "name": "global_channels_id",
          "columns": [
            "id"
          ]
        }
      },
      "uniqueConstraints": {}
    },
    "global_connections": {
      "name": "global_connections",
      "columns": {
        "channel": {
          "name": "channel",
          "type": "int",
          "primaryKey": false,
          "notNull": true,
          "autoincrement": false
        },
        "guild": {
          "name": "guild",
          "type": "varchar(20)",
          "primaryKey": false,
          "notNull": true,
          "autoincrement": false
        },
        "location": {
          "name": "location",
          "type": "varchar(20)",
          "primaryKey": false,
          "notNull": true,
          "autoincrement": false
        }
      },
      "indexes": {},
      "foreignKeys": {
        "global_connections_channel_global_channels_id_fk": {
          "name": "global_connections_channel_global_channels_id_fk",
          "tableFrom": "global_connections",
          "tableTo": "global_channels",
          "columnsFrom": [
            "channel"
          ],
          "columnsTo": [
            "id"
          ],
          "onDelete": "cascade",
          "onUpdate": "cascade"
        }
      },
      "compositePrimaryKeys": {
        "global_connections_location": {
          "name": "global_connections_location",
          "columns": [
            "location"
          ]
        }
      },
      "uniqueConstraints": {
        "unq_channel_guild": {
          "name": "unq_channel_guild",
          "columns": [
            "channel",
            "guild"
          ]
        }
      }
    },
    "global_filter_terms": {
      "name": "global_filter_terms",
      "columns": {
        "id": {
          "name": "id",
          "type": "int",
          "primaryKey": false,
          "notNull": true,
          "autoincrement": true
        },
        "filter": {
          "name": "filter",
          "type": "int",
          "primaryKey": false,
          "notNull": true,
          "autoincrement": false
        },
        "term": {
          "name": "term",
          "type": "text",
          "primaryKey": false,
          "notNull": true,
          "autoincrement": false
        },
        "regex": {
          "name": "regex",
          "type": "boolean",
          "primaryKey": false,
          "notNull": true,
          "autoincrement": false
        }
      },
      "indexes": {
        "idx_filter": {
          "name": "idx_filter",
          "columns": [
            "filter"
          ],
          "isUnique": false
        }
      },
      "foreignKeys": {
        "global_filter_terms_filter_global_filters_id_fk": {
          "name": "global_filter_terms_filter_global_filters_id_fk",
          "tableFrom": "global_filter_terms",
          "tableTo": "global_filters",
          "columnsFrom": [
            "filter"
          ],
          "columnsTo": [
            "id"
          ],
          "onDelete": "cascade",
          "onUpdate": "cascade"
        }
      },
      "compositePrimaryKeys": {
        "global_filter_terms_id": {
          "name": "global_filter_terms_id",
          "columns": [
            "id"
          ]
        }
      },
      "uniqueConstraints": {}
    },
    "global_filters": {
      "name": "global_filters",
      "columns": {
        "id": {
          "name": "id",
          "type": "int",
          "primaryKey": false,
          "notNull": true,
          "autoincrement": true
        },
        "name": {
          "name": "name",
          "type": "varchar(80)",
          "primaryKey": false,
          "notNull": true,
          "autoincrement": false
        }
      },
      "indexes": {},
      "foreignKeys": {},
      "compositePrimaryKeys": {
        "global_filters_id": {
          "name": "global_filters_id",
          "columns": [
            "id"
          ]
        }
      },
      "uniqueConstraints": {}
    },
    "global_info_on_user_request_instances": {
      "name": "global_info_on_user_request_instances",
      "columns": {
        "ref": {
          "name": "ref",
          "type": "int",
          "primaryKey": false,
          "notNull": true,
          "autoincrement": false
        },
        "guild": {
          "name": "guild",
          "type": "varchar(20)",
          "primaryKey": false,
          "notNull": true,
          "autoincrement": false
        },
        "channel": {
          "name": "channel",
          "type": "varchar(20)",
          "primaryKey": false,
          "notNull": true,
          "autoincrement": false
        },
        "message": {
          "name": "message",
          "type": "varchar(20)",
          "primaryKey": false,
          "notNull": true,
          "autoincrement": false
        }
      },
      "indexes": {
        "idx_ref": {
          "name": "idx_ref",
          "columns": [
            "ref"
          ],
          "isUnique": false
        }
      },
      "foreignKeys": {
        "global_info_on_user_request_instances_ref_global_messages_id_fk": {
          "name": "global_info_on_user_request_instances_ref_global_messages_id_fk",
          "tableFrom": "global_info_on_user_request_instances",
          "tableTo": "global_messages",
          "columnsFrom": [
            "ref"
          ],
          "columnsTo": [
            "id"
          ],
          "onDelete": "cascade",
          "onUpdate": "cascade"
        }
      },
      "compositePrimaryKeys": {
        "global_info_on_user_request_instances_message": {
          "name": "global_info_on_user_request_instances_message",
          "columns": [
            "message"
          ]
        }
      },
      "uniqueConstraints": {}
    },
    "global_info_on_user_requests": {
      "name": "global_info_on_user_requests",
      "columns": {
        "ref": {
          "name": "ref",
          "type": "int",
          "primaryKey": false,
          "notNull": true,
          "autoincrement": false
        },
        "text": {
          "name": "text",
          "type": "text",
          "primaryKey": false,
          "notNull": true,
          "autoincrement": false
        },
        "count": {
          "name": "count",
          "type": "int",
          "primaryKey": false,
          "notNull": true,
          "autoincrement": false
        }
      },
      "indexes": {},
      "foreignKeys": {
        "global_info_on_user_requests_ref_global_messages_id_fk": {
          "name": "global_info_on_user_requests_ref_global_messages_id_fk",
          "tableFrom": "global_info_on_user_requests",
          "tableTo": "global_messages",
          "columnsFrom": [
            "ref"
          ],
          "columnsTo": [
            "id"
          ],
          "onDelete": "cascade",
          "onUpdate": "cascade"
        }
      },
      "compositePrimaryKeys": {
        "global_info_on_user_requests_ref": {
          "name": "global_info_on_user_requests_ref",
          "columns": [
            "ref"
          ]
        }
      },
      "uniqueConstraints": {}
    },
    "global_message_instances": {
      "name": "global_message_instances",
      "columns": {
        "ref": {
          "name": "ref",
          "type": "int",
          "primaryKey": false,
          "notNull": true,
          "autoincrement": false
        },
        "guild": {
          "name": "guild",
          "type": "varchar(20)",
          "primaryKey": false,
          "notNull": true,
          "autoincrement": false
        },
        "channel": {
          "name": "channel",
          "type": "varchar(20)",
          "primaryKey": false,
          "notNull": true,
          "autoincrement": false
        },
        "message": {
          "name": "message",
          "type": "varchar(20)",
          "primaryKey": false,
          "notNull": true,
          "autoincrement": false
        },
        "never_delete": {
          "name": "never_delete",
          "type": "boolean",
          "primaryKey": false,
          "notNull": true,
          "autoincrement": false,
          "default": false
        }
      },
      "indexes": {
        "idx_message": {
          "name": "idx_message",
          "columns": [
            "message"
          ],
          "isUnique": false
        }
      },
      "foreignKeys": {
        "global_message_instances_ref_global_messages_id_fk": {
          "name": "global_message_instances_ref_global_messages_id_fk",
          "tableFrom": "global_message_instances",
          "tableTo": "global_messages",
          "columnsFrom": [
            "ref"
          ],
          "columnsTo": [
            "id"
          ],
          "onDelete": "cascade",
          "onUpdate": "cascade"
        }
      },
      "compositePrimaryKeys": {},
      "uniqueConstraints": {}
    },
    "global_messages": {
      "name": "global_messages",
      "columns": {
        "id": {
          "name": "id",
          "type": "int",
          "primaryKey": false,
          "notNull": true,
          "autoincrement": true
        },
        "channel": {
          "name": "channel",
          "type": "int",
          "primaryKey": false,
          "notNull": true,
          "autoincrement": false
        },
        "author": {
          "name": "author",
          "type": "varchar(20)",
          "primaryKey": false,
          "notNull": true,
          "autoincrement": false
        },
        "origin_guild": {
          "name": "origin_guild",
          "type": "varchar(20)",
          "primaryKey": false,
          "notNull": true,
          "autoincrement": false
        },
        "origin_channel": {
          "name": "origin_channel",
          "type": "varchar(20)",
          "primaryKey": false,
          "notNull": true,
          "autoincrement": false
        },
        "origin_message": {
          "name": "origin_message",
          "type": "varchar(20)",
          "primaryKey": false,
          "notNull": true,
          "autoincrement": false
        },
        "deleted": {
          "name": "deleted",
          "type": "boolean",
          "primaryKey": false,
          "notNull": true,
          "autoincrement": false,
          "default": false
        },
        "time": {
          "name": "time",
          "type": "bigint",
          "primaryKey": false,
          "notNull": true,
          "autoincrement": false
        },
        "content": {
          "name": "content",
          "type": "text",
          "primaryKey": false,
          "notNull": true,
          "autoincrement": false
        },
        "embeds": {
          "name": "embeds",
          "type": "json",
          "primaryKey": false,
          "notNull": false,
          "autoincrement": false
        },
        "attachments": {
          "name": "attachments",
          "type": "json",
          "primaryKey": false,
          "notNull": false,
          "autoincrement": false
        },
        "username": {
          "name": "username",
          "type": "varchar(80)",
          "primaryKey": false,
          "notNull": true,
          "autoincrement": false
        },
        "avatar": {
          "name": "avatar",
          "type": "text",
          "primaryKey": false,
          "notNull": true,
          "autoincrement": false
        }
      },
      "indexes": {
        "idx_author": {
          "name": "idx_author",
          "columns": [
            "author"
          ],
          "isUnique": false
        }
      },
      "foreignKeys": {
        "global_messages_channel_global_channels_id_fk": {
          "name": "global_messages_channel_global_channels_id_fk",
          "tableFrom": "global_messages",
          "tableTo": "global_channels",
          "columnsFrom": [
            "channel"
          ],
          "columnsTo": [
            "id"
          ],
          "onDelete": "cascade",
          "onUpdate": "cascade"
        }
      },
      "compositePrimaryKeys": {
        "global_messages_id": {
          "name": "global_messages_id",
          "columns": [
            "id"
          ]
        }
      },
      "uniqueConstraints": {}
    },
    "global_mod_logs": {
      "name": "global_mod_logs",
      "columns": {
        "user": {
          "name": "user",
          "type": "varchar(20)",
          "primaryKey": false,
          "notNull": true,
          "autoincrement": false
        },
        "actor": {
          "name": "actor",
          "type": "varchar(20)",
          "primaryKey": false,
          "notNull": true,
          "autoincrement": false
        },
        "action": {
          "name": "action",
          "type": "enum('warn','ban','unban')",
          "primaryKey": false,
          "notNull": true,
          "autoincrement": false
        },
        "reason": {
          "name": "reason",
          "type": "varchar(256)",
          "primaryKey": false,
          "notNull": false,
          "autoincrement": false
        }
      },
      "indexes": {},
      "foreignKeys": {},
      "compositePrimaryKeys": {},
      "uniqueConstraints": {}
    },
    "global_mods": {
      "name": "global_mods",
      "columns": {
        "channel": {
          "name": "channel",
          "type": "int",
          "primaryKey": false,
          "notNull": true,
          "autoincrement": false
        },
        "user": {
          "name": "user",
          "type": "varchar(20)",
          "primaryKey": false,
          "notNull": true,
          "autoincrement": false
        }
      },
      "indexes": {},
      "foreignKeys": {
        "global_mods_channel_global_channels_id_fk": {
          "name": "global_mods_channel_global_channels_id_fk",
          "tableFrom": "global_mods",
          "tableTo": "global_channels",
          "columnsFrom": [
            "channel"
          ],
          "columnsTo": [
            "id"
          ],
          "onDelete": "cascade",
          "onUpdate": "cascade"
        }
      },
      "compositePrimaryKeys": {
        "global_mods_channel_user_pk": {
          "name": "global_mods_channel_user_pk",
          "columns": [
            "channel",
            "user"
          ]
        }
      },
      "uniqueConstraints": {}
    },
    "global_webhook_tracker": {
      "name": "global_webhook_tracker",
      "columns": {
        "webhook": {
          "name": "webhook",
          "type": "varchar(20)",
          "primaryKey": false,
          "notNull": true,
          "autoincrement": false
        }
      },
      "indexes": {},
      "foreignKeys": {},
      "compositePrimaryKeys": {
        "global_webhook_tracker_webhook": {
          "name": "global_webhook_tracker_webhook",
          "columns": [
            "webhook"
          ]
        }
      },
      "uniqueConstraints": {}
    },
    "guild_staff": {
      "name": "guild_staff",
      "columns": {
        "guild": {
          "name": "guild",
          "type": "varchar(20)",
          "primaryKey": false,
          "notNull": true,
          "autoincrement": false
        },
        "user": {
          "name": "user",
          "type": "varchar(20)",
          "primaryKey": false,
          "notNull": true,
          "autoincrement": false
        }
      },
      "indexes": {},
      "foreignKeys": {
        "guild_staff_guild_guilds_id_fk": {
          "name": "guild_staff_guild_guilds_id_fk",
          "tableFrom": "guild_staff",
          "tableTo": "guilds",
          "columnsFrom": [
            "guild"
          ],
          "columnsTo": [
            "id"
          ],
          "onDelete": "cascade",
          "onUpdate": "cascade"
        }
      },
      "compositePrimaryKeys": {
        "guild_staff_guild_user_pk": {
          "name": "guild_staff_guild_user_pk",
          "columns": [
            "guild",
            "user"
          ]
        }
      },
      "uniqueConstraints": {}
    },
    "guilds": {
      "name": "guilds",
      "columns": {
        "id": {
          "name": "id",
          "type": "varchar(20)",
          "primaryKey": false,
          "notNull": true,
          "autoincrement": false
        },
        "mascot": {
          "name": "mascot",
          "type": "varchar(32)",
          "primaryKey": false,
          "notNull": true,
          "autoincrement": false
        },
        "name": {
          "name": "name",
          "type": "text",
          "primaryKey": false,
          "notNull": true,
          "autoincrement": false
        },
        "invite": {
          "name": "invite",
          "type": "text",
          "primaryKey": false,
          "notNull": true,
          "autoincrement": false
        },
        "image": {
          "name": "image",
          "type": "text",
          "primaryKey": false,
          "notNull": true,
          "autoincrement": false
        },
        "owner": {
          "name": "owner",
          "type": "varchar(20)",
          "primaryKey": false,
          "notNull": true,
          "autoincrement": false
        },
        "advisor": {
          "name": "advisor",
          "type": "varchar(20)",
          "primaryKey": false,
          "notNull": false,
          "autoincrement": false
        },
        "delegated": {
          "name": "delegated",
          "type": "boolean",
          "primaryKey": false,
          "notNull": true,
          "autoincrement": false
        },
        "role_color": {
          "name": "role_color",
          "type": "int",
          "primaryKey": false,
          "notNull": true,
          "autoincrement": false
        },
        "role_name": {
          "name": "role_name",
          "type": "varchar(80)",
          "primaryKey": false,
          "notNull": true,
          "autoincrement": false
        },
        "hq_role": {
          "name": "hq_role",
          "type": "varchar(20)",
          "primaryKey": false,
          "notNull": true,
          "autoincrement": false
        },
        "hub_role": {
          "name": "hub_role",
          "type": "varchar(20)",
          "primaryKey": false,
          "notNull": true,
          "autoincrement": false
        }
      },
      "indexes": {},
      "foreignKeys": {
        "guilds_mascot_characters_id_fk": {
          "name": "guilds_mascot_characters_id_fk",
          "tableFrom": "guilds",
          "tableTo": "characters",
          "columnsFrom": [
            "mascot"
          ],
          "columnsTo": [
            "id"
          ],
          "onDelete": "cascade",
          "onUpdate": "cascade"
        }
      },
      "compositePrimaryKeys": {
        "guilds_id": {
          "name": "guilds_id",
          "columns": [
            "id"
          ]
        }
      },
      "uniqueConstraints": {}
    },
    "hub_partner_list_location": {
      "name": "hub_partner_list_location",
      "columns": {
        "id": {
          "name": "id",
          "type": "int",
          "primaryKey": false,
          "notNull": true,
          "autoincrement": false
        },
        "message": {
          "name": "message",
          "type": "varchar(20)",
          "primaryKey": false,
          "notNull": true,
          "autoincrement": false
        }
      },
      "indexes": {},
      "foreignKeys": {},
      "compositePrimaryKeys": {
        "hub_partner_list_location_id": {
          "name": "hub_partner_list_location_id",
          "columns": [
            "id"
          ]
        }
      },
      "uniqueConstraints": {}
    },
    "induction_polls": {
      "name": "induction_polls",
      "columns": {
        "ref": {
          "name": "ref",
          "type": "int",
          "primaryKey": false,
          "notNull": true,
          "autoincrement": false
        },
        "mode": {
          "name": "mode",
          "type": "enum('normal','pre-approve','positive-tiebreak','negative-tiebreak')",
          "primaryKey": false,
          "notNull": true,
          "autoincrement": false
        }
      },
      "indexes": {},
      "foreignKeys": {
        "induction_polls_ref_polls_id_fk": {
          "name": "induction_polls_ref_polls_id_fk",
          "tableFrom": "induction_polls",
          "tableTo": "polls",
          "columnsFrom": [
            "ref"
          ],
          "columnsTo": [
            "id"
          ],
          "onDelete": "cascade",
          "onUpdate": "cascade"
        }
      },
      "compositePrimaryKeys": {
        "induction_polls_ref": {
          "name": "induction_polls_ref",
          "columns": [
            "ref"
          ]
        }
      },
      "uniqueConstraints": {}
    },
    "induction_votes": {
      "name": "induction_votes",
      "columns": {
        "ref": {
          "name": "ref",
          "type": "int",
          "primaryKey": false,
          "notNull": true,
          "autoincrement": false
        },
        "user": {
          "name": "user",
          "type": "varchar(20)",
          "primaryKey": false,
          "notNull": true,
          "autoincrement": false
        },
        "vote": {
          "name": "vote",
          "type": "enum('induct','preapprove','reject','extend','abstain')",
          "primaryKey": false,
          "notNull": true,
          "autoincrement": false
        }
      },
      "indexes": {},
      "foreignKeys": {
        "induction_votes_ref_polls_id_fk": {
          "name": "induction_votes_ref_polls_id_fk",
          "tableFrom": "induction_votes",
          "tableTo": "polls",
          "columnsFrom": [
            "ref"
          ],
          "columnsTo": [
            "id"
          ],
          "onDelete": "cascade",
          "onUpdate": "cascade"
        }
      },
      "compositePrimaryKeys": {
        "induction_votes_ref_user_pk": {
          "name": "induction_votes_ref_user_pk",
          "columns": [
            "ref",
            "user"
          ]
        }
      },
      "uniqueConstraints": {}
    },
    "polls": {
      "name": "polls",
      "columns": {
        "id": {
          "name": "id",
          "type": "int",
          "primaryKey": false,
          "notNull": true,
          "autoincrement": true
        },
        "type": {
          "name": "type",
          "type": "enum('decline-observation','cancel-observation','induction','election','proposal','selection')",
          "primaryKey": false,
          "notNull": true,
          "autoincrement": false
        },
        "message": {
          "name": "message",
          "type": "varchar(20)",
          "primaryKey": false,
          "notNull": true,
          "autoincrement": false
        },
        "reminder": {
          "name": "reminder",
          "type": "bigint",
          "primaryKey": false,
          "notNull": false,
          "autoincrement": false
        },
        "deadline": {
          "name": "deadline",
          "type": "bigint",
          "primaryKey": false,
          "notNull": true,
          "autoincrement": false
        },
        "closed": {
          "name": "closed",
          "type": "boolean",
          "primaryKey": false,
          "notNull": true,
          "autoincrement": false
        },
        "truly_closed": {
          "name": "truly_closed",
          "type": "boolean",
          "primaryKey": false,
          "notNull": true,
          "autoincrement": false
        },
        "errored": {
          "name": "errored",
          "type": "boolean",
          "primaryKey": false,
          "notNull": true,
          "autoincrement": false,
          "default": false
        }
      },
      "indexes": {},
      "foreignKeys": {},
      "compositePrimaryKeys": {
        "polls_id": {
          "name": "polls_id",
          "columns": [
            "id"
          ]
        }
      },
      "uniqueConstraints": {}
    },
    "proposal_polls": {
      "name": "proposal_polls",
      "columns": {
        "ref": {
          "name": "ref",
          "type": "int",
          "primaryKey": false,
          "notNull": true,
          "autoincrement": false
        },
        "question": {
          "name": "question",
          "type": "varchar(1024)",
          "primaryKey": false,
          "notNull": true,
          "autoincrement": false
        }
      },
      "indexes": {},
      "foreignKeys": {
        "proposal_polls_ref_polls_id_fk": {
          "name": "proposal_polls_ref_polls_id_fk",
          "tableFrom": "proposal_polls",
          "tableTo": "polls",
          "columnsFrom": [
            "ref"
          ],
          "columnsTo": [
            "id"
          ],
          "onDelete": "cascade",
          "onUpdate": "cascade"
        }
      },
      "compositePrimaryKeys": {
        "proposal_polls_ref": {
          "name": "proposal_polls_ref",
          "columns": [
            "ref"
          ]
        }
      },
      "uniqueConstraints": {}
    },
    "proposal_votes": {
      "name": "proposal_votes",
      "columns": {
        "ref": {
          "name": "ref",
          "type": "int",
          "primaryKey": false,
          "notNull": true,
          "autoincrement": false
        },
        "user": {
          "name": "user",
          "type": "varchar(20)",
          "primaryKey": false,
          "notNull": true,
          "autoincrement": false
        },
        "vote": {
          "name": "vote",
          "type": "enum('accept','reject','abstain')",
          "primaryKey": false,
          "notNull": true,
          "autoincrement": false
        }
      },
      "indexes": {},
      "foreignKeys": {
        "proposal_votes_ref_polls_id_fk": {
          "name": "proposal_votes_ref_polls_id_fk",
          "tableFrom": "proposal_votes",
          "tableTo": "polls",
          "columnsFrom": [
            "ref"
          ],
          "columnsTo": [
            "id"
          ],
          "onDelete": "cascade",
          "onUpdate": "cascade"
        }
      },
      "compositePrimaryKeys": {
        "proposal_votes_ref_user_pk": {
          "name": "proposal_votes_ref_user_pk",
          "columns": [
            "ref",
            "user"
          ]
        }
      },
      "uniqueConstraints": {}
    },
    "selection_polls": {
      "name": "selection_polls",
      "columns": {
        "ref": {
          "name": "ref",
          "type": "int",
          "primaryKey": false,
          "notNull": true,
          "autoincrement": false
        },
        "question": {
          "name": "question",
          "type": "varchar(1024)",
          "primaryKey": false,
          "notNull": true,
          "autoincrement": false
        },
        "options": {
          "name": "options",
          "type": "json",
          "primaryKey": false,
          "notNull": true,
          "autoincrement": false
        },
        "minimum": {
          "name": "minimum",
          "type": "int",
          "primaryKey": false,
          "notNull": true,
          "autoincrement": false
        },
        "maximum": {
          "name": "maximum",
          "type": "int",
          "primaryKey": false,
          "notNull": true,
          "autoincrement": false
        }
      },
      "indexes": {},
      "foreignKeys": {
        "selection_polls_ref_polls_id_fk": {
          "name": "selection_polls_ref_polls_id_fk",
          "tableFrom": "selection_polls",
          "tableTo": "polls",
          "columnsFrom": [
            "ref"
          ],
          "columnsTo": [
            "id"
          ],
          "onDelete": "cascade",
          "onUpdate": "cascade"
        }
      },
      "compositePrimaryKeys": {
        "selection_polls_ref": {
          "name": "selection_polls_ref",
          "columns": [
            "ref"
          ]
        }
      },
      "uniqueConstraints": {}
    },
    "selection_votes": {
      "name": "selection_votes",
      "columns": {
        "ref": {
          "name": "ref",
          "type": "int",
          "primaryKey": false,
          "notNull": true,
          "autoincrement": false
        },
        "user": {
          "name": "user",
          "type": "varchar(20)",
          "primaryKey": false,
          "notNull": true,
          "autoincrement": false
        },
        "vote": {
          "name": "vote",
          "type": "json",
          "primaryKey": false,
          "notNull": true,
          "autoincrement": false
        }
      },
      "indexes": {},
      "foreignKeys": {
        "selection_votes_ref_polls_id_fk": {
          "name": "selection_votes_ref_polls_id_fk",
          "tableFrom": "selection_votes",
          "tableTo": "polls",
          "columnsFrom": [
            "ref"
          ],
          "columnsTo": [
            "id"
          ],
          "onDelete": "cascade",
          "onUpdate": "cascade"
        }
      },
      "compositePrimaryKeys": {
        "selection_votes_ref_user_pk": {
          "name": "selection_votes_ref_user_pk",
          "columns": [
            "ref",
            "user"
          ]
        }
      },
      "uniqueConstraints": {}
    },
    "users": {
      "name": "users",
      "columns": {
        "id": {
          "name": "id",
          "type": "varchar(20)",
          "primaryKey": false,
          "notNull": true,
          "autoincrement": false
        },
        "observer": {
          "name": "observer",
          "type": "boolean",
          "primaryKey": false,
          "notNull": true,
          "autoincrement": false,
          "default": false
        },
        "observer_since": {
          "name": "observer_since",
          "type": "bigint",
          "primaryKey": false,
          "notNull": true,
          "autoincrement": false,
          "default": 0
        },
        "global_nickname": {
          "name": "global_nickname",
          "type": "varchar(40)",
          "primaryKey": false,
          "notNull": false,
          "autoincrement": false,
          "default": "null"
        }
      },
      "indexes": {},
      "foreignKeys": {},
      "compositePrimaryKeys": {
        "users_id": {
          "name": "users_id",
          "columns": [
            "id"
          ]
        }
      },
      "uniqueConstraints": {}
    },
    "vote_tracker": {
      "name": "vote_tracker",
      "columns": {
        "poll": {
          "name": "poll",
          "type": "int",
          "primaryKey": false,
          "notNull": true,
          "autoincrement": false
        },
        "user": {
          "name": "user",
          "type": "varchar(20)",
          "primaryKey": false,
          "notNull": true,
          "autoincrement": false
        }
      },
      "indexes": {},
      "foreignKeys": {
        "vote_tracker_poll_polls_id_fk": {
          "name": "vote_tracker_poll_polls_id_fk",
          "tableFrom": "vote_tracker",
          "tableTo": "polls",
          "columnsFrom": [
            "poll"
          ],
          "columnsTo": [
            "id"
          ],
          "onDelete": "cascade",
          "onUpdate": "cascade"
        }
      },
      "compositePrimaryKeys": {
        "vote_tracker_poll_user_pk": {
          "name": "vote_tracker_poll_user_pk",
          "columns": [
            "poll",
            "user"
          ]
        }
      },
      "uniqueConstraints": {}
    }
  },
  "schemas": {},
  "_meta": {
    "schemas": {},
    "tables": {},
    "columns": {}
  }
}